searcher/__init__.py
searcher/converters.py
searcher/models.py
searcher/search.py
searcher-0.1.0.dist-info/METADATA
searcher-0.1.0.dist-info/RECORD
searcher-0.1.0.dist-info/WHEEL
searcher-0.1.0.dist-info/top_level.txt
